{
    "pools": [
        {
            "rolls": 1,
            "entries": [
                {
                    "type": "minecraft:item",
                    "name": "minecraft:paper",
                    "functions": [
                        {
                            "function": "minecraft:set_name",
                            "entity": "this",
                            "name": {
                                "text": "Harry Potter 2",
                                "italic": false
                            }
                        },
                        {
                            "function": "minecraft:set_lore",
                            "entity": "this",
                            "lore": [
                                {
                                    "text": "1980-present",
                                    "italic": false
                                },
                                {
                                    "text": "The boy who lived.",
                                    "italic": false
                                },
                                {
                                    "text": "#15 Famous Wizards Cards",
                                    "italic": false,
                                    "color": "#FFFFFF"
                                }
                            ],
                            "replace": true
                        },
                        {
                            "function": "minecraft:set_nbt",
                            "tag": "{CustomModelData:10004,WizardCard:1b,harry_potter_2:1b}"
                        }
                    ]
                }
            ]
        }
    ]
}