{
    "pools": [
        {
            "rolls": 1,
            "entries": [
                {
                    "type": "minecraft:item",
                    "name": "minecraft:paper",
                    "functions": [
                        {
                            "function": "minecraft:set_name",
                            "entity": "this",
                            "name": {
                                "text": "Ignatia Wildsmith",
                                "italic": false
                            }
                        },
                        {
                            "function": "minecraft:set_lore",
                            "entity": "this",
                            "lore": [
                                {
                                    "text": "1227-1320",
                                    "italic": false
                                },
                                {
                                    "text": "Ignatia Wildsmith was a",
                                    "italic": false
                                },
                                {
                                    "text": "wizarding inventor and the",
                                    "italic": false
                                },
                                {
                                    "text": "creator of Floo powder.",
                                    "italic": false
                                },
                                {
                                    "text": "#62 Silver",
                                    "italic": false,
                                    "color": "#878E9F"
                                }
                            ],
                            "replace": true
                        },
                        {
                            "function": "minecraft:set_nbt",
                            "tag": "{CustomModelData:10001,WizardCard:1b}"
                        }
                    ]
                }
            ]
        }
    ]
}